{
  "annotations": {
    "list": [
      {
        "builtIn": 1,
        "datasource": {
          "type": "grafana",
          "uid": "-- Grafana --"
        },
        "enable": true,
        "hide": true,
        "iconColor": "rgba(0, 211, 255, 1)",
        "name": "Annotations & Alerts",
        "target": {
          "limit": 100,
          "matchAny": false,
          "tags": [],
          "type": "dashboard"
        },
        "type": "dashboard"
      }
    ]
  },
  "editable": true,
  "fiscalYearStartMonth": 0,
  "graphTooltip": 0,
  "id": 11,
  "links": [],
  "liveNow": false,
  "panels": [
    {
      "collapsed": false,
      "gridPos": {
        "h": 1,
        "w": 24,
        "x": 0,
        "y": 0
      },
      "id": 16,
      "panels": [],
      "title": "Dev-seg",
      "type": "row"
    },
    {
      "datasource": {
        "type": "prometheus",
        "uid": "${datasource}"
      },
      "fieldConfig": {
        "defaults": {
          "color": {
            "mode": "palette-classic"
          },
          "custom": {
            "axisCenteredZero": false,
            "axisColorMode": "text",
            "axisLabel": "",
            "axisPlacement": "auto",
            "barAlignment": 0,
            "drawStyle": "line",
            "fillOpacity": 0,
            "gradientMode": "none",
            "hideFrom": {
              "legend": false,
              "tooltip": false,
              "viz": false
            },
            "lineInterpolation": "linear",
            "lineWidth": 2,
            "pointSize": 5,
            "scaleDistribution": {
              "type": "linear"
            },
            "showPoints": "auto",
            "spanNulls": false,
            "stacking": {
              "group": "A",
              "mode": "none"
            },
            "thresholdsStyle": {
              "mode": "off"
            }
          },
          "mappings": [],
          "thresholds": {
            "mode": "absolute",
            "steps": [
              {
                "color": "green",
                "value": null
              },
              {
                "color": "red",
                "value": 80
              }
            ]
          }
        },
        "overrides": []
      },
      "gridPos": {
        "h": 1,
        "w": 7,
        "x": 0,
        "y": 1
      },
      "id": 18,
      "options": {
        "legend": {
          "calcs": [],
          "displayMode": "list",
          "placement": "bottom",
          "showLegend": true
        },
        "tooltip": {
          "mode": "single",
          "sort": "none"
        }
      },
      "targets": [
        {
          "datasource": {
            "type": "prometheus",
            "uid": "${datasource}"
          },
          "expr": "",
          "instant": false,
          "range": true,
          "refId": "A"
        }
      ],
      "title": "Cassandra",
      "type": "timeseries"
    },
    {
      "datasource": {
        "type": "prometheus",
        "uid": "${datasource}"
      },
      "fieldConfig": {
        "defaults": {
          "color": {
            "mode": "palette-classic"
          },
          "custom": {
            "axisCenteredZero": false,
            "axisColorMode": "text",
            "axisLabel": "",
            "axisPlacement": "auto",
            "barAlignment": 0,
            "drawStyle": "line",
            "fillOpacity": 0,
            "gradientMode": "none",
            "hideFrom": {
              "legend": false,
              "tooltip": false,
              "viz": false
            },
            "lineInterpolation": "linear",
            "lineWidth": 2,
            "pointSize": 5,
            "scaleDistribution": {
              "type": "linear"
            },
            "showPoints": "auto",
            "spanNulls": false,
            "stacking": {
              "group": "A",
              "mode": "none"
            },
            "thresholdsStyle": {
              "mode": "off"
            }
          },
          "mappings": [],
          "thresholds": {
            "mode": "absolute",
            "steps": [
              {
                "color": "green",
                "value": null
              },
              {
                "color": "red",
                "value": 80
              }
            ]
          }
        },
        "overrides": []
      },
      "gridPos": {
        "h": 1,
        "w": 7,
        "x": 7,
        "y": 1
      },
      "id": 19,
      "options": {
        "legend": {
          "calcs": [],
          "displayMode": "list",
          "placement": "bottom",
          "showLegend": true
        },
        "tooltip": {
          "mode": "single",
          "sort": "none"
        }
      },
      "targets": [
        {
          "datasource": {
            "type": "prometheus",
            "uid": "${datasource}"
          },
          "expr": "",
          "instant": false,
          "range": true,
          "refId": "A"
        }
      ],
      "title": "Kafka",
      "type": "timeseries"
    },
    {
      "datasource": {
        "type": "prometheus",
        "uid": "${datasource}"
      },
      "fieldConfig": {
        "defaults": {
          "color": {
            "mode": "palette-classic"
          },
          "custom": {
            "axisCenteredZero": false,
            "axisColorMode": "text",
            "axisLabel": "",
            "axisPlacement": "auto",
            "barAlignment": 0,
            "drawStyle": "line",
            "fillOpacity": 0,
            "gradientMode": "none",
            "hideFrom": {
              "legend": false,
              "tooltip": false,
              "viz": false
            },
            "lineInterpolation": "linear",
            "lineWidth": 2,
            "pointSize": 5,
            "scaleDistribution": {
              "type": "linear"
            },
            "showPoints": "auto",
            "spanNulls": false,
            "stacking": {
              "group": "A",
              "mode": "none"
            },
            "thresholdsStyle": {
              "mode": "off"
            }
          },
          "mappings": [],
          "thresholds": {
            "mode": "absolute",
            "steps": [
              {
                "color": "green",
                "value": null
              },
              {
                "color": "red",
                "value": 80
              }
            ]
          }
        },
        "overrides": []
      },
      "gridPos": {
        "h": 1,
        "w": 8,
        "x": 14,
        "y": 1
      },
      "id": 20,
      "options": {
        "legend": {
          "calcs": [],
          "displayMode": "list",
          "placement": "bottom",
          "showLegend": true
        },
        "tooltip": {
          "mode": "single",
          "sort": "none"
        }
      },
      "targets": [
        {
          "datasource": {
            "type": "prometheus",
            "uid": "${datasource}"
          },
          "expr": "",
          "instant": false,
          "range": true,
          "refId": "A"
        }
      ],
      "title": "Kubernetes",
      "type": "timeseries"
    },
    {
      "datasource": {
        "type": "prometheus",
        "uid": "${datasource}"
      },
      "description": "",
      "fieldConfig": {
        "defaults": {
          "color": {
            "mode": "palette-classic"
          },
          "custom": {
            "axisCenteredZero": false,
            "axisColorMode": "text",
            "axisLabel": "",
            "axisPlacement": "auto",
            "barAlignment": 0,
            "drawStyle": "line",
            "fillOpacity": 50,
            "gradientMode": "opacity",
            "hideFrom": {
              "legend": false,
              "tooltip": false,
              "viz": false
            },
            "lineInterpolation": "linear",
            "lineWidth": 1,
            "pointSize": 5,
            "scaleDistribution": {
              "type": "linear"
            },
            "showPoints": "never",
            "spanNulls": false,
            "stacking": {
              "group": "A",
              "mode": "none"
            },
            "thresholdsStyle": {
              "mode": "off"
            }
          },
          "links": [],
          "mappings": [],
          "min": 0,
          "thresholds": {
            "mode": "absolute",
            "steps": [
              {
                "color": "green",
                "value": null
              },
              {
                "color": "red",
                "value": 80
              }
            ]
          },
          "unit": "bytes"
        },
        "overrides": [
          {
            "matcher": {
              "id": "byName",
              "options": "max"
            },
            "properties": [
              {
                "id": "custom.fillOpacity",
                "value": 0
              }
            ]
          }
        ]
      },
      "gridPos": {
        "h": 8,
        "w": 7,
        "x": 0,
        "y": 2
      },
      "id": 6,
      "interval": "$interval",
      "options": {
        "legend": {
          "calcs": [
            "lastNotNull"
          ],
          "displayMode": "table",
          "placement": "bottom",
          "showLegend": true
        },
        "tooltip": {
          "mode": "multi",
          "sort": "none"
        }
      },
      "pluginVersion": "9.2.3",
      "targets": [
        {
          "datasource": {
            "type": "prometheus",
            "uid": "${datasource}"
          },
          "editorMode": "code",
          "expr": "sum by (instance) (cassandra_keyspace_totaldiskspaceused{datacenter=\"$datacenter\", cluster=\"$cluster\", instance=~\"$instance\"})",
          "interval": "$interval",
          "intervalFactor": 2,
          "legendFormat": "{{ instance }} - used",
          "range": true,
          "refId": "A"
        }
      ],
      "title": "Disk Used by instance",
      "type": "timeseries"
    },
    {
      "datasource": {
        "type": "prometheus",
        "uid": "${datasource}"
      },
      "description": "",
      "fieldConfig": {
        "defaults": {
          "color": {
            "mode": "palette-classic"
          },
          "custom": {
            "axisCenteredZero": false,
            "axisColorMode": "text",
            "axisLabel": "",
            "axisPlacement": "auto",
            "fillOpacity": 80,
            "gradientMode": "none",
            "hideFrom": {
              "legend": false,
              "tooltip": false,
              "viz": false
            },
            "lineWidth": 1,
            "scaleDistribution": {
              "type": "linear"
            },
            "thresholdsStyle": {
              "mode": "off"
            }
          },
          "decimals": 2,
          "links": [],
          "mappings": [],
          "thresholds": {
            "mode": "absolute",
            "steps": [
              {
                "color": "green",
                "value": null
              },
              {
                "color": "red",
                "value": 80
              }
            ]
          },
          "unit": "bytes"
        },
        "overrides": []
      },
      "gridPos": {
        "h": 8,
        "w": 7,
        "x": 7,
        "y": 2
      },
      "id": 26,
      "links": [],
      "options": {
        "barRadius": 0,
        "barWidth": 0.97,
        "fullHighlight": false,
        "groupWidth": 0.7,
        "legend": {
          "calcs": [],
          "displayMode": "list",
          "placement": "bottom",
          "showLegend": true
        },
        "orientation": "auto",
        "showValue": "auto",
        "stacking": "none",
        "tooltip": {
          "mode": "single",
          "sort": "none"
        },
        "xTickLabelRotation": 0,
        "xTickLabelSpacing": 0
      },
      "pluginVersion": "9.2.1",
      "targets": [
        {
          "datasource": {
            "type": "prometheus",
            "uid": "${datasource}"
          },
          "editorMode": "code",
          "expr": "sort(sum(kafka_log_size{job=\"$job\",instance=~\"$broker\"})by(instance))",
          "format": "time_series",
          "instant": true,
          "interval": "",
          "intervalFactor": 1,
          "legendFormat": "Instance Broker:  {{instance}}",
          "refId": "A"
        }
      ],
      "title": "Disk used by kafka",
      "type": "barchart"
    },
    {
      "datasource": {
        "type": "prometheus",
        "uid": "${datasource}"
      },
      "description": "",
      "fieldConfig": {
        "defaults": {
          "mappings": [],
          "noValue": "0",
          "thresholds": {
            "mode": "absolute",
            "steps": [
              {
                "color": "rgb(255, 255, 255)",
                "value": null
              }
            ]
          },
          "unit": "bytes"
        },
        "overrides": []
      },
      "gridPos": {
        "h": 3,
        "w": 8,
        "x": 14,
        "y": 2
      },
      "id": 12,
      "options": {
        "colorMode": "none",
        "graphMode": "none",
        "justifyMode": "auto",
        "orientation": "auto",
        "reduceOptions": {
          "calcs": [
            "mean"
          ],
          "fields": "",
          "values": false
        },
        "text": {},
        "textMode": "auto"
      },
      "pluginVersion": "10.0.3",
      "targets": [
        {
          "datasource": {
            "type": "prometheus",
            "uid": "${datasource}"
          },
          "editorMode": "code",
          "exemplar": true,
          "expr": "sum(node_memory_MemTotal_bytes{job=\"node-exporter\"} - node_memory_MemAvailable_bytes{job=\"node-exporter\"})",
          "interval": "",
          "legendFormat": "Real",
          "range": true,
          "refId": "A"
        },
        {
          "datasource": {
            "type": "prometheus",
            "uid": "${datasource}"
          },
          "editorMode": "code",
          "expr": "sum(kube_pod_container_resource_requests{unit=\"byte\"})",
          "hide": false,
          "legendFormat": "Requests",
          "range": true,
          "refId": "B"
        },
        {
          "datasource": {
            "type": "prometheus",
            "uid": "${datasource}"
          },
          "editorMode": "code",
          "expr": "sum(kube_pod_container_resource_limits{unit=\"byte\"})",
          "hide": false,
          "legendFormat": "Limits",
          "range": true,
          "refId": "C"
        },
        {
          "datasource": {
            "type": "prometheus",
            "uid": "${datasource}"
          },
          "editorMode": "code",
          "expr": "sum(machine_memory_bytes)",
          "hide": false,
          "legendFormat": "Total",
          "range": true,
          "refId": "D"
        }
      ],
      "title": "RAM Usage",
      "type": "stat"
    },
    {
      "datasource": {
        "type": "prometheus",
        "uid": "${datasource}"
      },
      "description": "",
      "fieldConfig": {
        "defaults": {
          "mappings": [],
          "noValue": "0",
          "thresholds": {
            "mode": "absolute",
            "steps": [
              {
                "color": "rgb(255, 255, 255)",
                "value": null
              }
            ]
          },
          "unit": "none"
        },
        "overrides": []
      },
      "gridPos": {
        "h": 3,
        "w": 8,
        "x": 14,
        "y": 5
      },
      "id": 4,
      "options": {
        "colorMode": "none",
        "graphMode": "none",
        "justifyMode": "center",
        "orientation": "auto",
        "reduceOptions": {
          "calcs": [
            "mean"
          ],
          "fields": "",
          "values": false
        },
        "text": {},
        "textMode": "auto"
      },
      "pluginVersion": "10.0.3",
      "targets": [
        {
          "datasource": {
            "type": "prometheus",
            "uid": "${datasource}"
          },
          "editorMode": "code",
          "exemplar": true,
          "expr": "sum(1-rate(node_cpu_seconds_total{mode=\"idle\", job=\"node-exporter\"}[$__rate_interval]))",
          "interval": "",
          "legendFormat": "Real",
          "range": true,
          "refId": "A"
        },
        {
          "datasource": {
            "type": "prometheus",
            "uid": "${datasource}"
          },
          "editorMode": "code",
          "expr": "sum(kube_pod_container_resource_requests{unit=\"core\"})",
          "hide": false,
          "legendFormat": "Requests",
          "range": true,
          "refId": "B"
        },
        {
          "datasource": {
            "type": "prometheus",
            "uid": "${datasource}"
          },
          "editorMode": "code",
          "expr": "sum(kube_pod_container_resource_limits{unit=\"core\"})",
          "hide": false,
          "legendFormat": "Limits",
          "range": true,
          "refId": "C"
        },
        {
          "datasource": {
            "type": "prometheus",
            "uid": "${datasource}"
          },
          "editorMode": "code",
          "expr": "sum(machine_cpu_cores)",
          "hide": false,
          "legendFormat": "Total",
          "range": true,
          "refId": "D"
        }
      ],
      "title": "CPU Usage",
      "type": "stat"
    },
    {
      "datasource": {
        "type": "prometheus",
        "uid": "${datasource}"
      },
      "description": "",
      "fieldConfig": {
        "defaults": {
          "color": {
            "mode": "palette-classic"
          },
          "custom": {
            "axisCenteredZero": false,
            "axisColorMode": "text",
            "axisLabel": "",
            "axisPlacement": "auto",
            "barAlignment": 0,
            "drawStyle": "line",
            "fillOpacity": 25,
            "gradientMode": "opacity",
            "hideFrom": {
              "legend": false,
              "tooltip": false,
              "viz": false
            },
            "lineInterpolation": "smooth",
            "lineWidth": 2,
            "pointSize": 5,
            "scaleDistribution": {
              "type": "linear"
            },
            "showPoints": "never",
            "spanNulls": true,
            "stacking": {
              "group": "A",
              "mode": "none"
            },
            "thresholdsStyle": {
              "mode": "off"
            }
          },
          "decimals": 2,
          "mappings": [],
          "thresholds": {
            "mode": "absolute",
            "steps": [
              {
                "color": "green",
                "value": null
              },
              {
                "color": "red",
                "value": 80
              }
            ]
          },
          "unit": "percentunit"
        },
        "overrides": []
      },
      "gridPos": {
        "h": 6,
        "w": 8,
        "x": 14,
        "y": 8
      },
      "id": 24,
      "options": {
        "legend": {
          "calcs": [
            "min",
            "max",
            "lastNotNull"
          ],
          "displayMode": "table",
          "placement": "right",
          "showLegend": true,
          "sortBy": "Max",
          "sortDesc": true
        },
        "tooltip": {
          "mode": "single",
          "sort": "none"
        }
      },
      "pluginVersion": "8.3.3",
      "targets": [
        {
          "datasource": {
            "type": "prometheus",
            "uid": "${datasource}"
          },
          "editorMode": "code",
          "exemplar": true,
          "expr": "avg(1-rate(node_cpu_seconds_total{mode=\"idle\", job=\"node-exporter\"}[$__rate_interval])) by (instance)",
          "interval": "$resolution",
          "legendFormat": "{{ node }}",
          "range": true,
          "refId": "A"
        }
      ],
      "title": "CPU Utilization by instance",
      "type": "timeseries"
    },
    {
      "datasource": {
        "type": "prometheus",
        "uid": "${datasource}"
      },
      "description": "",
      "fieldConfig": {
        "defaults": {
          "color": {
            "mode": "palette-classic"
          },
          "custom": {
            "axisCenteredZero": false,
            "axisColorMode": "text",
            "axisLabel": "",
            "axisPlacement": "auto",
            "barAlignment": 0,
            "drawStyle": "line",
            "fillOpacity": 10,
            "gradientMode": "opacity",
            "hideFrom": {
              "legend": false,
              "tooltip": false,
              "viz": false
            },
            "lineInterpolation": "linear",
            "lineWidth": 1,
            "pointSize": 5,
            "scaleDistribution": {
              "type": "linear"
            },
            "showPoints": "never",
            "spanNulls": true,
            "stacking": {
              "group": "A",
              "mode": "none"
            },
            "thresholdsStyle": {
              "mode": "off"
            }
          },
          "links": [],
          "mappings": [],
          "min": 0,
          "thresholds": {
            "mode": "absolute",
            "steps": [
              {
                "color": "green",
                "value": null
              },
              {
                "color": "red",
                "value": 80
              }
            ]
          },
          "unit": "bytes"
        },
        "overrides": []
      },
      "gridPos": {
        "h": 6,
        "w": 7,
        "x": 0,
        "y": 10
      },
      "id": 8,
      "interval": "1m",
      "options": {
        "legend": {
          "calcs": [],
          "displayMode": "list",
          "placement": "right",
          "showLegend": true
        },
        "tooltip": {
          "mode": "multi",
          "sort": "none"
        }
      },
      "pluginVersion": "8.5.3",
      "targets": [
        {
          "datasource": {
            "type": "prometheus",
            "uid": "${datasource}"
          },
          "editorMode": "code",
          "expr": "sum by (instance)(jvm_memory_bytes_used{datacenter=\"$datacenter\", cluster=\"$cluster\", area=\"heap\" ,job=\"cassandra_discovery\"}) + sum by (instance)(jvm_memory_bytes_used{datacenter=\"$datacenter\", cluster=\"$cluster\", area=\"nonheap\" ,job=\"cassandra_discovery\"})",
          "legendFormat": "{{ instance }} - used",
          "range": true,
          "refId": "A"
        },
        {
          "datasource": {
            "type": "prometheus",
            "uid": "${datasource}"
          },
          "editorMode": "code",
          "expr": "sum by (instance)(jvm_memory_bytes_max{datacenter=\"$datacenter\", cluster=\"$cluster\", area=\"heap\" ,job=\"cassandra_discovery\"})",
          "hide": false,
          "legendFormat": "{{instance}} - max",
          "range": true,
          "refId": "B"
        }
      ],
      "title": "JVM Memory Used",
      "type": "timeseries"
    },
    {
      "datasource": {
        "type": "prometheus",
        "uid": "${datasource}"
      },
      "description": "",
      "fieldConfig": {
        "defaults": {
          "color": {
            "mode": "palette-classic"
          },
          "custom": {
            "axisCenteredZero": false,
            "axisColorMode": "text",
            "axisLabel": "",
            "axisPlacement": "auto",
            "barAlignment": 0,
            "drawStyle": "line",
            "fillOpacity": 10,
            "gradientMode": "opacity",
            "hideFrom": {
              "legend": false,
              "tooltip": false,
              "viz": false
            },
            "lineInterpolation": "linear",
            "lineWidth": 1,
            "pointSize": 5,
            "scaleDistribution": {
              "type": "linear"
            },
            "showPoints": "never",
            "spanNulls": true,
            "stacking": {
              "group": "A",
              "mode": "none"
            },
            "thresholdsStyle": {
              "mode": "off"
            }
          },
          "links": [],
          "mappings": [],
          "min": 0,
          "thresholds": {
            "mode": "absolute",
            "steps": [
              {
                "color": "green",
                "value": null
              },
              {
                "color": "red",
                "value": 80
              }
            ]
          },
          "unit": "bytes"
        },
        "overrides": []
      },
      "gridPos": {
        "h": 6,
        "w": 7,
        "x": 7,
        "y": 10
      },
      "id": 27,
      "interval": "1m",
      "options": {
        "legend": {
          "calcs": [],
          "displayMode": "list",
          "placement": "right",
          "showLegend": true
        },
        "tooltip": {
          "mode": "multi",
          "sort": "none"
        }
      },
      "pluginVersion": "8.5.3",
      "targets": [
        {
          "datasource": {
            "type": "prometheus",
            "uid": "${datasource}"
          },
          "editorMode": "code",
          "expr": "sum by (instance)(jvm_memory_bytes_used{datacenter=\"$datacenter\", cluster=\"$cluster\", area=\"heap\" ,job=\"kafka_discovery\"}) + sum by (instance)(jvm_memory_bytes_used{datacenter=\"$datacenter\", cluster=\"$cluster\", area=\"nonheap\" ,job=\"kafka_discovery\"})",
          "legendFormat": "{{ instance }} - used",
          "range": true,
          "refId": "A"
        },
        {
          "datasource": {
            "type": "prometheus",
            "uid": "${datasource}"
          },
          "editorMode": "code",
          "expr": "sum by (instance)(jvm_memory_bytes_max{datacenter=\"$datacenter\", cluster=\"$cluster\", area=\"heap\" ,job=\"kafka_discovery\"})",
          "hide": false,
          "legendFormat": "{{instance}} - max",
          "range": true,
          "refId": "B"
        }
      ],
      "title": "JVM Memory Used",
      "type": "timeseries"
    },
    {
      "datasource": {
        "type": "prometheus",
        "uid": "${datasource}"
      },
      "description": "",
      "fieldConfig": {
        "defaults": {
          "color": {
            "mode": "palette-classic"
          },
          "custom": {
            "axisCenteredZero": false,
            "axisColorMode": "text",
            "axisLabel": "MEMORY",
            "axisPlacement": "auto",
            "barAlignment": 0,
            "drawStyle": "line",
            "fillOpacity": 25,
            "gradientMode": "opacity",
            "hideFrom": {
              "legend": false,
              "tooltip": false,
              "viz": false
            },
            "lineInterpolation": "smooth",
            "lineWidth": 2,
            "pointSize": 5,
            "scaleDistribution": {
              "type": "linear"
            },
            "showPoints": "never",
            "spanNulls": true,
            "stacking": {
              "group": "A",
              "mode": "none"
            },
            "thresholdsStyle": {
              "mode": "off"
            }
          },
          "mappings": [],
          "thresholds": {
            "mode": "absolute",
            "steps": [
              {
                "color": "green",
                "value": null
              },
              {
                "color": "red",
                "value": 80
              }
            ]
          },
          "unit": "bytes"
        },
        "overrides": []
      },
      "gridPos": {
        "h": 7,
        "w": 8,
        "x": 14,
        "y": 14
      },
      "id": 22,
      "options": {
        "legend": {
          "calcs": [
            "last"
          ],
          "displayMode": "table",
          "placement": "right",
          "showLegend": true,
          "sortBy": "Max",
          "sortDesc": true
        },
        "tooltip": {
          "mode": "single",
          "sort": "none"
        }
      },
      "pluginVersion": "8.3.3",
      "targets": [
        {
          "datasource": {
            "type": "prometheus",
            "uid": "${datasource}"
          },
          "editorMode": "code",
          "exemplar": true,
          "expr": "sum(node_memory_MemTotal_bytes{job=\"node-exporter\"} - node_memory_MemAvailable_bytes{job=\"node-exporter\"}) by (instance)",
          "interval": "$resolution",
          "legendFormat": "{{ node}}",
          "range": true,
          "refId": "A"
        },
        {
          "datasource": {
            "type": "prometheus",
            "uid": "${datasource}"
          },
          "editorMode": "code",
          "expr": "sum(node_memory_MemTotal_bytes{job=\"node-exporter\"}) by (instance)",
          "hide": false,
          "legendFormat": "{{instance}}-TOTAL",
          "range": true,
          "refId": "B"
        }
      ],
      "title": "Memory Utilization by instance",
      "type": "timeseries"
    },
    {
      "datasource": {
        "type": "prometheus",
        "uid": "${datasource}"
      },
      "description": "",
      "fieldConfig": {
        "defaults": {
          "decimals": 1,
          "displayName": "Uptime - ${__series.name}",
          "mappings": [
            {
              "options": {
                "match": "null",
                "result": {
                  "text": "N/A"
                }
              },
              "type": "special"
            }
          ],
          "thresholds": {
            "mode": "absolute",
            "steps": [
              {
                "color": "red",
                "value": null
              },
              {
                "color": "dark-green",
                "value": 1
              }
            ]
          },
          "unit": "s"
        },
        "overrides": []
      },
      "gridPos": {
        "h": 5,
        "w": 7,
        "x": 0,
        "y": 16
      },
      "id": 14,
      "links": [],
      "options": {
        "colorMode": "background",
        "graphMode": "none",
        "justifyMode": "center",
        "orientation": "auto",
        "reduceOptions": {
          "calcs": [
            "last"
          ],
          "fields": "",
          "values": false
        },
        "textMode": "auto"
      },
      "pluginVersion": "10.0.3",
      "targets": [
        {
          "datasource": {
            "type": "prometheus",
            "uid": "${datasource}"
          },
          "editorMode": "code",
          "expr": "time() - process_start_time_seconds{instance!=\"\", job=\"cassandra_discovery\"}",
          "interval": "",
          "legendFormat": "{{ instance }}",
          "range": true,
          "refId": "A"
        }
      ],
      "type": "stat"
    },
    {
      "datasource": {
        "type": "prometheus",
        "uid": "${datasource}"
      },
      "description": "",
      "fieldConfig": {
        "defaults": {
          "color": {
            "mode": "thresholds"
          },
          "displayName": "Messages In Per Sec",
          "mappings": [],
          "noValue": "0",
          "thresholds": {
            "mode": "absolute",
            "steps": [
              {
                "color": "green",
                "value": null
              }
            ]
          },
          "unit": "locale"
        },
        "overrides": []
      },
      "gridPos": {
        "h": 5,
        "w": 3,
        "x": 7,
        "y": 16
      },
      "id": 29,
      "options": {
        "colorMode": "background",
        "graphMode": "area",
        "justifyMode": "auto",
        "orientation": "auto",
        "reduceOptions": {
          "calcs": [
            "last"
          ],
          "fields": "",
          "values": false
        },
        "textMode": "auto"
      },
      "pluginVersion": "10.0.3",
      "targets": [
        {
          "datasource": {
            "type": "prometheus",
            "uid": "${datasource}"
          },
          "expr": "sum(rate(kafka_server_brokertopicmetrics_messagesin_total{job=\"$job\",topic=\"\"}[1m]))",
          "interval": "",
          "legendFormat": "Total messages in per sec ",
          "refId": "A"
        }
      ],
      "type": "stat"
    },
    {
      "datasource": {
        "type": "prometheus",
        "uid": "${datasource}"
      },
      "description": "",
      "fieldConfig": {
        "defaults": {
          "color": {
            "mode": "thresholds"
          },
          "mappings": [
            {
              "options": {
                "match": "null",
                "result": {
                  "text": "N/A"
                }
              },
              "type": "special"
            }
          ],
          "thresholds": {
            "mode": "absolute",
            "steps": [
              {
                "color": "#d44a3a",
                "value": null
              },
              {
                "color": "rgba(237, 129, 40, 0.89)",
                "value": 2
              },
              {
                "color": "#299c46",
                "value": 3
              }
            ]
          },
          "unit": "none"
        },
        "overrides": []
      },
      "gridPos": {
        "h": 5,
        "w": 2,
        "x": 10,
        "y": 16
      },
      "id": 2,
      "links": [],
      "maxDataPoints": 100,
      "options": {
        "colorMode": "value",
        "graphMode": "area",
        "justifyMode": "auto",
        "orientation": "horizontal",
        "reduceOptions": {
          "calcs": [
            "lastNotNull"
          ],
          "fields": "",
          "values": false
        },
        "textMode": "auto"
      },
      "pluginVersion": "10.0.3",
      "targets": [
        {
          "datasource": {
            "type": "prometheus",
            "uid": "${datasource}"
          },
          "editorMode": "code",
          "expr": "count(kafka_server_replicamanager_leadercount)",
          "format": "time_series",
          "instant": false,
          "interval": "",
          "intervalFactor": 1,
          "legendFormat": "",
          "refId": "A"
        }
      ],
      "title": "Brokers Online",
      "type": "stat"
    },
    {
      "datasource": {
        "type": "prometheus",
        "uid": "${datasource}"
      },
      "description": "",
      "fieldConfig": {
        "defaults": {
          "color": {
            "mode": "thresholds"
          },
          "mappings": [
            {
              "options": {
                "match": "null",
                "result": {
                  "text": "N/A"
                }
              },
              "type": "special"
            }
          ],
          "thresholds": {
            "mode": "absolute",
            "steps": [
              {
                "color": "green",
                "value": null
              },
              {
                "color": "red",
                "value": 80
              }
            ]
          },
          "unit": "none"
        },
        "overrides": []
      },
      "gridPos": {
        "h": 5,
        "w": 2,
        "x": 12,
        "y": 16
      },
      "id": 31,
      "links": [],
      "maxDataPoints": 100,
      "options": {
        "colorMode": "value",
        "graphMode": "area",
        "justifyMode": "auto",
        "orientation": "horizontal",
        "reduceOptions": {
          "calcs": [
            "lastNotNull"
          ],
          "fields": "",
          "values": false
        },
        "textMode": "auto"
      },
      "pluginVersion": "10.0.3",
      "targets": [
        {
          "datasource": {
            "type": "prometheus",
            "uid": "${datasource}"
          },
          "editorMode": "code",
          "expr": "sum(kafka_controller_kafkacontroller_globaltopiccount{job=~\"$job\"})",
          "format": "time_series",
          "hide": false,
          "interval": "",
          "intervalFactor": 2,
          "legendFormat": "",
          "range": true,
          "refId": "A"
        }
      ],
      "title": "Total of Topics",
      "type": "stat"
    }
  ],
  "refresh": "10s",
  "schemaVersion": 38,
  "style": "dark",
  "tags": [],
  "templating": {
    "list": [
      {
        "current": {
          "selected": false,
          "text": "CD6",
          "value": "CD6"
        },
        "hide": 0,
        "includeAll": false,
        "multi": false,
        "name": "datasource",
        "options": [],
        "query": "prometheus",
        "queryValue": "",
        "refresh": 1,
        "regex": "",
        "skipUrlSync": false,
        "type": "datasource"
      },
      {
        "auto": true,
        "auto_count": 30,
        "auto_min": "10s",
        "current": {
          "selected": false,
          "text": "auto",
          "value": "$__auto_interval_resolution"
        },
        "hide": 0,
        "name": "resolution",
        "options": [
          {
            "selected": true,
            "text": "auto",
            "value": "$__auto_interval_resolution"
          },
          {
            "selected": false,
            "text": "30s",
            "value": "30s"
          },
          {
            "selected": false,
            "text": "1m",
            "value": "1m"
          },
          {
            "selected": false,
            "text": "10m",
            "value": "10m"
          },
          {
            "selected": false,
            "text": "30m",
            "value": "30m"
          },
          {
            "selected": false,
            "text": "1h",
            "value": "1h"
          },
          {
            "selected": false,
            "text": "6h",
            "value": "6h"
          },
          {
            "selected": false,
            "text": "12h",
            "value": "12h"
          },
          {
            "selected": false,
            "text": "1d",
            "value": "1d"
          },
          {
            "selected": false,
            "text": "7d",
            "value": "7d"
          },
          {
            "selected": false,
            "text": "14d",
            "value": "14d"
          },
          {
            "selected": false,
            "text": "30d",
            "value": "30d"
          }
        ],
        "query": "30s,1m,10m,30m,1h,6h,12h,1d,7d,14d,30d",
        "queryValue": "",
        "refresh": 2,
        "skipUrlSync": false,
        "type": "interval"
      },
      {
        "current": {
          "isNone": true,
          "selected": false,
          "text": "None",
          "value": ""
        },
        "datasource": {
          "type": "prometheus",
          "uid": "${datasource}"
        },
        "definition": "label_values(cassandra_table_totaldiskspaceused_count{cluster=\"$cluster\"}, datacenter)",
        "hide": 0,
        "includeAll": false,
        "multi": false,
        "name": "datacenter",
        "options": [],
        "query": {
          "query": "label_values(cassandra_table_totaldiskspaceused_count{cluster=\"$cluster\"}, datacenter)",
          "refId": "StandardVariableQuery"
        },
        "refresh": 1,
        "regex": "",
        "skipUrlSync": false,
        "sort": 1,
        "type": "query"
      },
      {
        "current": {
          "isNone": true,
          "selected": false,
          "text": "None",
          "value": ""
        },
        "datasource": {
          "type": "prometheus",
          "uid": "${datasource}"
        },
        "definition": "label_values(cassandra_table_totaldiskspaceused_count, cluster)",
        "hide": 0,
        "includeAll": false,
        "multi": false,
        "name": "cluster",
        "options": [],
        "query": {
          "query": "label_values(cassandra_table_totaldiskspaceused_count, cluster)",
          "refId": "StandardVariableQuery"
        },
        "refresh": 1,
        "regex": "",
        "skipUrlSync": false,
        "sort": 1,
        "type": "query"
      },
      {
        "current": {
          "isNone": true,
          "selected": false,
          "text": "None",
          "value": ""
        },
        "datasource": {
          "type": "prometheus",
          "uid": "${datasource}"
        },
        "definition": "label_values(cassandra_table_totaldiskspaceused_count{datacenter=\"$datacenter\", cluster=\"$cluster\"}, keyspace)",
        "hide": 0,
        "includeAll": false,
        "multi": false,
        "name": "keyspace",
        "options": [],
        "query": {
          "query": "label_values(cassandra_table_totaldiskspaceused_count{datacenter=\"$datacenter\", cluster=\"$cluster\"}, keyspace)",
          "refId": "StandardVariableQuery"
        },
        "refresh": 1,
        "regex": "",
        "skipUrlSync": false,
        "sort": 1,
        "type": "query"
      },
      {
        "allValue": ".*",
        "current": {
          "selected": true,
          "text": [
            "All"
          ],
          "value": [
            "$__all"
          ]
        },
        "datasource": {
          "type": "prometheus",
          "uid": "${datasource}"
        },
        "definition": "label_values(cassandra_table_totaldiskspaceused_count{datacenter=\"$datacenter\", cluster=\"$cluster\", keyspace=\"$keyspace\"}, table)",
        "hide": 0,
        "includeAll": true,
        "multi": true,
        "name": "table",
        "options": [],
        "query": {
          "query": "label_values(cassandra_table_totaldiskspaceused_count{datacenter=\"$datacenter\", cluster=\"$cluster\", keyspace=\"$keyspace\"}, table)",
          "refId": "StandardVariableQuery"
        },
        "refresh": 1,
        "regex": "",
        "skipUrlSync": false,
        "sort": 1,
        "type": "query"
      },
      {
        "allValue": ".*",
        "current": {
          "selected": true,
          "text": [
            "All"
          ],
          "value": [
            "$__all"
          ]
        },
        "datasource": {
          "type": "prometheus",
          "uid": "${datasource}"
        },
        "definition": "label_values(cassandra_table_totaldiskspaceused_count{datacenter=\"$datacenter\", cluster=\"$cluster\",}, instance)",
        "hide": 0,
        "includeAll": true,
        "multi": true,
        "name": "instance",
        "options": [],
        "query": {
          "query": "label_values(cassandra_table_totaldiskspaceused_count{datacenter=\"$datacenter\", cluster=\"$cluster\",}, instance)",
          "refId": "StandardVariableQuery"
        },
        "refresh": 1,
        "regex": "",
        "skipUrlSync": false,
        "sort": 1,
        "type": "query"
      },
      {
        "hide": 2,
        "name": "interval",
        "query": "1m",
        "skipUrlSync": false,
        "type": "constant"
      },
      {
        "current": {
          "selected": false,
          "text": [
            "All"
          ],
          "value": [
            "$__all"
          ]
        },
        "datasource": {
          "type": "prometheus",
          "uid": "prometheus"
        },
        "definition": "label_values(kafka_controller_kafkacontroller_controllerstate{job=\"$job\"}, instance)",
        "hide": 0,
        "includeAll": true,
        "label": "Broker",
        "multi": true,
        "name": "broker",
        "options": [],
        "query": {
          "query": "label_values(kafka_controller_kafkacontroller_controllerstate{job=\"$job\"}, instance)",
          "refId": "StandardVariableQuery"
        },
        "refresh": 1,
        "regex": "",
        "skipUrlSync": false,
        "sort": 0,
        "type": "query"
      },
      {
        "current": {
          "selected": true,
          "text": [
            "All"
          ],
          "value": [
            "$__all"
          ]
        },
        "datasource": {
          "type": "prometheus",
          "uid": "prometheus"
        },
        "definition": "label_values(kafka_cluster_partition_replicascount{job=\"$job\"}, topic)",
        "hide": 0,
        "includeAll": true,
        "label": "Topic",
        "multi": true,
        "name": "topic",
        "options": [],
        "query": {
          "query": "label_values(kafka_cluster_partition_replicascount{job=\"$job\"}, topic)",
          "refId": "StandardVariableQuery"
        },
        "refresh": 2,
        "regex": "",
        "skipUrlSync": false,
        "sort": 0,
        "type": "query"
      },
      {
        "current": {
          "selected": false,
          "text": "kafka_discovery",
          "value": "kafka_discovery"
        },
        "datasource": {
          "type": "prometheus",
          "uid": "prometheus"
        },
        "definition": "label_values(kafka_controller_kafkacontroller_controllerstate, job)",
        "hide": 0,
        "includeAll": false,
        "label": "job",
        "multi": false,
        "name": "job",
        "options": [],
        "query": {
          "query": "label_values(kafka_controller_kafkacontroller_controllerstate, job)",
          "refId": "StandardVariableQuery"
        },
        "refresh": 1,
        "regex": "",
        "skipUrlSync": false,
        "sort": 0,
        "type": "query"
      }
    ]
  },
  "time": {
    "from": "now-30m",
    "to": "now"
  },
  "timepicker": {},
  "timezone": "",
  "title": "New dashboard",
  "uid": "vGD1ygeVz",
  "version": 3,
  "weekStart": ""
}